robhan_cdk_lib/aws_mwaa/__init__.py
robhan_cdk_lib/aws_mwaa/py.typed
robhan_cdk_lib/aws_mwaa/_jsii/__init__.py
robhan_cdk_lib/aws_mwaa/_jsii/aws_mwaa@0.0.83.jsii.tgz
robhan_cdk_lib_aws_mwaa-0.0.83.dist-info/LICENSE
robhan_cdk_lib_aws_mwaa-0.0.83.dist-info/METADATA
robhan_cdk_lib_aws_mwaa-0.0.83.dist-info/WHEEL
robhan_cdk_lib_aws_mwaa-0.0.83.dist-info/top_level.txt
robhan_cdk_lib_aws_mwaa-0.0.83.dist-info/RECORD
