Metadata-Version: 2.1
Name: robhan_cdk_lib.aws_mwaa
Version: 0.0.83
Summary: AWS CDK Construct Library for Amazon Managed Workflows for Apache Airflow
Home-page: https://github.com/robert-hanuschke/cdk-aws_mwaa.git
Author: Robert Hanuschke<robhan-cdk-lib@hanuschke.eu>
License: MIT
Project-URL: Source, https://github.com/robert-hanuschke/cdk-aws_mwaa.git
Classifier: Intended Audience :: Developers
Classifier: Operating System :: OS Independent
Classifier: Programming Language :: JavaScript
Classifier: Programming Language :: Python :: 3 :: Only
Classifier: Programming Language :: Python :: 3.9
Classifier: Programming Language :: Python :: 3.10
Classifier: Programming Language :: Python :: 3.11
Classifier: Typing :: Typed
Classifier: Development Status :: 5 - Production/Stable
Classifier: License :: OSI Approved
Requires-Python: ~=3.9
License-File: LICENSE
Requires-Dist: aws-cdk-lib <3.0.0,>=2.224.0
Requires-Dist: constructs <11.0.0,>=10.0.5
Requires-Dist: jsii <2.0.0,>=1.126.0
Requires-Dist: publication >=0.0.3
Requires-Dist: robhan-cdk-lib.utils <0.0.160,>=0.0.159
Requires-Dist: typeguard ==2.13.3
